{
  "unversionedId": "node_modules/rtlcss/CHANGELOG",
  "id": "node_modules/rtlcss/CHANGELOG",
  "title": "3.5.0 - 02 Nov. 2021",
  "description": "* Update dependencies. Thanks @XhmikosR",
  "source": "@site/node_modules/rtlcss/CHANGELOG.md",
  "sourceDirName": "node_modules/rtlcss",
  "slug": "/node_modules/rtlcss/CHANGELOG",
  "permalink": "/consul-release-controller/node_modules/rtlcss/CHANGELOG",
  "editUrl": "https://github.com/nicholasjackson/consul-release-controller/tree/main/docs/templates/shared/node_modules/rtlcss/CHANGELOG.md",
  "tags": [],
  "version": "current",
  "frontMatter": {},
  "sidebar": "tutorialSidebar",
  "previous": {
    "title": "RTLCSS",
    "permalink": "/consul-release-controller/node_modules/rtlcss/"
  },
  "next": {
    "title": "run-parallel [![travis][travis-image]][travis-url] [![npm][npm-image]][npm-url] [![downloads][downloads-image]][downloads-url] [![javascript style guide][standard-image]][standard-url]",
    "permalink": "/consul-release-controller/node_modules/run-parallel/"
  }
}