{
  "unversionedId": "node_modules/semver-diff/readme",
  "id": "node_modules/semver-diff/readme",
  "title": "semver-diff [![Build Status](https://travis-ci.org/sindresorhus/semver-diff.svg?branch=master)](https://travis-ci.org/sindresorhus/semver-diff)",
  "description": "Get the diff type of two semver versions: 0.0.1 0.0.2 → patch",
  "source": "@site/node_modules/semver-diff/readme.md",
  "sourceDirName": "node_modules/semver-diff",
  "slug": "/node_modules/semver-diff/",
  "permalink": "/consul-release-controller/node_modules/semver-diff/",
  "editUrl": "https://github.com/nicholasjackson/consul-release-controller/tree/main/docs/templates/shared/node_modules/semver-diff/readme.md",
  "tags": [],
  "version": "current",
  "frontMatter": {},
  "sidebar": "tutorialSidebar",
  "previous": {
    "title": "changes log",
    "permalink": "/consul-release-controller/node_modules/semver/CHANGELOG"
  },
  "next": {
    "title": "send",
    "permalink": "/consul-release-controller/node_modules/send/"
  }
}